<?xml version="1.0" encoding="UTF-8" standalone="no"?>
<nifty>
  <useStyles filename="nifty-default-styles.xml"/>
  <useControls filename="nifty-default-controls.xml"/>
  <screen id="start" controller="dynamicLoad.MyStartScreen">
    <layer childLayout="absolute" id="layer2">
      <image filename="Interface/imgs/img1.png" height="100%" id="image0" width="100%" x="0" y="0"/>
    </layer>
    <layer childLayout="absolute" id="layer3">
      <panel childLayout="absolute" height="30%" id="panel0" style="nifty-panel-simple" backgroundImage="Interface/imgs/bgp.png" width="50%" x="25%" y="35%" alpha="30%">
           <effect>
	          <onStartScreen name="move" timeType="exp" factor="3.5" direction="top" mode="in" length="500" inherit="true"/>
	          <onEndScreen name="move" timeType="exp" factor="3.5" direction="bottom" mode="out" length="500" inherit="true"/>
	        </effect>
        <control font="aurulent-sans-16.fnt" height="46px" id="label0" name="label" text="This is a serious learning adventure game" width="100%" x="0px" y="35"/>
        <control childLayout="center" height="33px" id="button0" label="Continue" name="button" x="30%" y="101">
            <interact onClick="startGame(hud)" />
        </control>
       
        <control childLayout="center" height="32px" id="button1" label="Quit" name="button" x="50%" y="101">
            <interact onClick="quitGame()"/>
        </control>
      </panel>
    </layer>
  </screen>
  <screen id="hud" controller="dynamicLoad.MyStartScreen">
    <layer childLayout="absolute" id="layer2">
      <image filename="Interface/imgs/img1.png" height="100%" id="image0" width="100%" x="0" y="0"/>
    </layer>
</screen>

<screen id="chatbar" controller="dynamicLoad.MyStartScreen">
    <layer childLayout="absolute" id="layer1"  >
      <panel childLayout="absolute" height="30%" id="panel0" style="nifty-panel-simple" width="35%" x="0%" y="70%" backgroundImage="Interface/imgs/bgp.png" alpha="30%">
          <effect>
	          <onStartScreen name="move" timeType="exp" factor="3.5" direction="left" mode="in" length="500" inherit="true"/>
	          <onEndScreen name="move" timeType="exp" factor="3.5" direction="bottom" mode="out" length="500" inherit="true"/>
	   </effect>
        <control height="25px" id="textfield2" name="textfield" width="100%" x="0" y="90%" color="#bbaa00">
             <interact onClick="quitGame()"/>
       </control>
       <control height="32px" id="connect" label="Connect" name="button" x="5%" y="0px">
            <interact onClick="connectServer()"/>
        </control>
      </panel>
    </layer>
 </screen>
</nifty>
